allure_pytest/__init__.py
allure_pytest/helper.py
allure_pytest/listener.py
allure_pytest/plugin.py
allure_pytest/utils.py
allure_pytest_acn-2.8.6.dist-info/METADATA
allure_pytest_acn-2.8.6.dist-info/WHEEL
allure_pytest_acn-2.8.6.dist-info/entry_points.txt
allure_pytest_acn-2.8.6.dist-info/top_level.txt
allure_pytest_acn-2.8.6.dist-info/RECORD
