Metadata-Version: 2.1
Name: allure-pytest-acn
Version: 2.8.6
Summary: Allure pytest integration
Home-page: https://github.com/allure-framework/allure-python
Author: QAMetaSoftware, Stanislav Seliverstov
Author-email: sseliverstov@qameta.io
License: Apache-2.0
Keywords: allure reporting pytest
Platform: UNKNOWN
Classifier: Development Status :: 5 - Production/Stable
Classifier: Framework :: Pytest
Classifier: Intended Audience :: Developers
Classifier: License :: OSI Approved :: Apache Software License
Classifier: Topic :: Software Development :: Quality Assurance
Classifier: Topic :: Software Development :: Testing
Requires-Dist: pytest (>=4.5.0)
Requires-Dist: six (>=1.9.0)
Requires-Dist: allure-python-commons-acn (==2.8.6)
